biosimulators_gillespy2/__init__.py
biosimulators_gillespy2/__main__.py
biosimulators_gillespy2/_version.py
biosimulators_gillespy2/core.py
biosimulators_gillespy2/data_model.py
biosimulators_gillespy2-0.1.37.dist-info/LICENSE
biosimulators_gillespy2-0.1.37.dist-info/METADATA
biosimulators_gillespy2-0.1.37.dist-info/WHEEL
biosimulators_gillespy2-0.1.37.dist-info/entry_points.txt
biosimulators_gillespy2-0.1.37.dist-info/top_level.txt
biosimulators_gillespy2-0.1.37.dist-info/RECORD
