Metadata-Version: 2.1
Name: biosimulators-gillespy2
Version: 0.1.37
Summary: BioSimulators-compliant command-line interface to the GillesPy2 simulation program.
Home-page: https://github.com/biosimulators/Biosimulators_GillesPy2
Download-URL: https://github.com/biosimulators/Biosimulators_GillesPy2
Author: BioSimulators Team
Author-email: info@biosimulators.org
License: MIT
Platform: UNKNOWN
Classifier: Development Status :: 3 - Alpha
Classifier: Intended Audience :: Science/Research
Classifier: License :: OSI Approved :: MIT License
Classifier: Topic :: Scientific/Engineering :: Bio-Informatics
License-File: LICENSE
Requires-Dist: biosimulators-utils[logging] (>=0.1.151)
Requires-Dist: gillespy2 (<=1.6.6,>=1.6.0)
Requires-Dist: kisao
Requires-Dist: lxml
Requires-Dist: numpy
Requires-Dist: python-libsbml
Provides-Extra: all
Requires-Dist: biosimulators-utils[containers] ; extra == 'all'
Requires-Dist: python-dateutil ; extra == 'all'
Provides-Extra: docs
Provides-Extra: tests
Requires-Dist: biosimulators-utils[containers] ; extra == 'tests'
Requires-Dist: python-dateutil ; extra == 'tests'
